vispm/__init__.py
vispm/animation/__init__.py
vispm/extensions/__init__.py
vispm/extensions/_base.py
vispm/extensions/dotted/__init__.py
vispm/extensions/dotted/colour_histogram.py
vispm/extensions/dotted/description_histogram.py
vispm/extensions/dotted/event_histogram.py
vispm/helpers/__init__.py
vispm/helpers/colours/__init__.py
vispm/helpers/colours/colourmaps.py
vispm/helpers/data/__init__.py
vispm/helpers/data/log_data.py
vispm/helpers/handlers/__init__.py
vispm/helpers/handlers/log_runners.py
vispm/helpers/imputers/__init__.py
vispm/helpers/imputers/colour_imputers.py
vispm/helpers/imputers/event_imputers.py
vispm/helpers/iters/__init__.py
vispm/helpers/iters/tools.py
vispm/helpers/metaclasses/__init__.py
vispm/helpers/metaclasses/pm4py.py
vispm/helpers/metaclasses/vispm.py
vispm/running/__init__.py
vispm/static/__init__.py
vispm/static/_base.py
vispm/static/dotted.py
vispm-0.0.6.2.dist-info/LICENSE
vispm-0.0.6.2.dist-info/METADATA
vispm-0.0.6.2.dist-info/WHEEL
vispm-0.0.6.2.dist-info/top_level.txt
vispm-0.0.6.2.dist-info/RECORD
