Metadata-Version: 2.1
Name: vispm
Version: 0.0.6.2
Summary: A visulisation package for process mining activties
Home-page: https://github.com/AdamBanham/vispm
Author: Adam
Author-email: adam_banham@hotmail.com
License: MIT
Project-URL: Bug Tracker, https://github.com/AdamBanham/vispm/issues
Classifier: Programming Language :: Python :: 3.9
Classifier: License :: OSI Approved :: MIT License
Classifier: Operating System :: OS Independent
Requires-Python: >=3.7
License-File: LICENSE
Requires-Dist: matplotlib (>=3.5.0)
